{
  "update_time": "2026-02-26T11:30:22.768961",
  "source_count": 3,
  "total_count": 3,
  "news": [
    {
      "title": "太空光伏，是否会成为下一个星辰大海？",
      "source": "华尔街见闻",
      "url": "https://wallstreetcn.com/articles/3766229",
      "time": "刚刚",
      "tag": "全球",
      "tagColor": "#10b981"
    },
    {
      "title": "创纪录资金涌入，却换来15年最差相对表现！美股光环褪去，美元警报响起？",
      "source": "华尔街见闻",
      "url": "https://wallstreetcn.com/articles/3766228",
      "time": "刚刚",
      "tag": "全球",
      "tagColor": "#10b981"
    },
    {
      "title": "比Citrini更悲观：美国AI效率越进步，分配越失灵",
      "source": "华尔街见闻",
      "url": "https://wallstreetcn.com/articles/3766151",
      "time": "刚刚",
      "tag": "数据中心",
      "tagColor": "#8b5cf6"
    }
  ]
}